{
  "project_info": {
    "project_number": "939337881014",
    "project_id": "len-den-ebb0c",
    "storage_bucket": "len-den-ebb0c.appspot.com"
  },
  "client": [
    {
      "client_info": {
        "mobilesdk_app_id": "1:939337881014:android:6967f71599b2e27286dd17",
        "android_client_info": {
          "package_name": "com.example.my_app"
        }
      },
      "oauth_client": [
        {
          "client_id": "939337881014-ah5tbn8dai9t9ladj2e3i924951lsi6p.apps.googleusercontent.com",
          "client_type": 1,
          "android_info": {
            "package_name": "com.example.my_app",
            "certificate_hash": "da18a0171abb718f23f706ec88ef6f251fb06cf7"
          }
        },
        {
          "client_id": "939337881014-d49cqbgactdvjreejfg9mbvbhj01ecuj.apps.googleusercontent.com",
          "client_type": 3
        }
      ],
      "api_key": [
        {
          "current_key": "AIzaSyC-6nVxcI1DMTqhUxqcRIJAEq0SV_cT8Hw"
        }
      ],
      "services": {
        "appinvite_service": {
          "other_platform_oauth_client": [
            {
              "client_id": "939337881014-d49cqbgactdvjreejfg9mbvbhj01ecuj.apps.googleusercontent.com",
              "client_type": 3
            }
          ]
        }
      }
    }
  ],
  "configuration_version": "1"
}